load_distributed/__init__.py
load_distributed/djikstra.py
load_distributed/main.py
load_distributed/metric_manager.py
load_distributed/node_manager.py
load_distributed/simulation_manager.py
load_distributed/layers/__init__.py
load_distributed/layers/application_layer.py
load_distributed/layers/layer_base.py
load_distributed/layers/link_layer.py
load_distributed/layers/networking_layer.py
load_distributed/layers/test_top_layer.py
load_distributed/layers/transport_layer.py
load_distributed/packet/__init__.py
load_distributed/packet/packet.py
load_distributed_routing-1.0.5.dist-info/LICENSE.txt
load_distributed_routing-1.0.5.dist-info/METADATA
load_distributed_routing-1.0.5.dist-info/WHEEL
load_distributed_routing-1.0.5.dist-info/entry_points.txt
load_distributed_routing-1.0.5.dist-info/top_level.txt
load_distributed_routing-1.0.5.dist-info/RECORD
