Metadata-Version: 2.1
Name: load-distributed-routing
Version: 1.0.5
Summary: Read the latest Real Python tutorials
Home-page: https://github.com/kylebrain/networking-final-project
Author: Kyle Brainard
Author-email: kbrainard@nevada.unr.edu
License: MIT
Platform: UNKNOWN
Requires-Dist: numpy
